README.md
setup.cfg
setup.py
HySpec/__init__.py
HySpec.egg-info/PKG-INFO
HySpec.egg-info/SOURCES.txt
HySpec.egg-info/dependency_links.txt
HySpec.egg-info/entry_points.txt
HySpec.egg-info/requires.txt
HySpec.egg-info/top_level.txt
spectralAdv/__init__.py
spectralAdv/atmosphericConversions.py
spectralAdv/atmosphericConversionsGUI.py
spectralAdv/bhattacharyyaComparison.py
spectralAdv/classification.py
spectralAdv/classificationResultsViewer.py
spectralAdv/classificationViewer.py
spectralAdv/discriminantAnalysisTest.py
spectralAdv/easterEggSounds.py
spectralAdv/feature_build_plot_temp.py
spectralAdv/imageViewer - Copy.py
spectralAdv/imageViewer.py
spectralAdv/imageViewerDialogs.py
spectralAdv/imageViewerLinker.py
spectralAdv/libraryManager.py
spectralAdv/libraryViewer.py
spectralAdv/materialIdentification.py
spectralAdv/materialIdentificationTabs.py
spectralAdv/materialIdentificationViewer.py
spectralAdv/open_image.py
spectralAdv/plotDisplay.py
spectralAdv/quac.py
spectralAdv/scatterplot2DViewer.py
spectralAdv/scatterplot3DViewer.py
spectralAdv/scatterplotViewer.py
spectralAdv/settings.py
spectralAdv/specTools.py
spectralAdv/specToolsMatplotlib.py
spectralAdv/spectraViewer.py
spectralAdv/spectralContrastViewer.py